rdascore/__init__.py
rdascore/analyze.py
rdascore/discrete_compactness.py
rdascore/smallestenclosingcircle.py
rdascore-4.1.0.dist-info/LICENSE
rdascore-4.1.0.dist-info/METADATA
rdascore-4.1.0.dist-info/WHEEL
rdascore-4.1.0.dist-info/top_level.txt
rdascore-4.1.0.dist-info/RECORD
